discord_analyzer.py
discord_analyzer-1.0.1.dist-info/LICENSE
discord_analyzer-1.0.1.dist-info/METADATA
discord_analyzer-1.0.1.dist-info/WHEEL
discord_analyzer-1.0.1.dist-info/entry_points.txt
discord_analyzer-1.0.1.dist-info/top_level.txt
discord_analyzer-1.0.1.dist-info/RECORD
