Metadata-Version: 2.1
Name: discord-analyzer
Version: 1.0.1
Summary: CLI tool for scanning Discord servers and visualizing statistics
Home-page: https://github.com/rodrigohpalmeirim/discord-analyzer
Author: Rodrigo Palmeirim
Author-email: rodrigohpalmeirim@hotmail.com
License: UNKNOWN
Keywords: python CLI Discord server scan analize statistics metrics table chart shell terminal
Platform: UNKNOWN
Classifier: Environment :: Console
Classifier: Programming Language :: Python :: 3
Classifier: Operating System :: OS Independent
Classifier: License :: OSI Approved :: GNU General Public License v3 or later (GPLv3+)
Classifier: Natural Language :: English
Requires-Python: >=3.6
License-File: LICENSE
Requires-Dist: discord
Requires-Dist: emoji
Requires-Dist: tabulate
Requires-Dist: pytz
Requires-Dist: tzlocal
